{
  "genres": [
    { "id": 28, "name": "Ação" },
    { "id": 12, "name": "Aventura" },
    { "id": 16, "name": "Animação" },
    { "id": 35, "name": "Comédia" },
    { "id": 80, "name": "Crime" },
    { "id": 99, "name": "Documentário" },
    { "id": 18, "name": "Drama" },
    { "id": 10751, "name": "Família" },
    { "id": 14, "name": "Fantasia" },
    { "id": 36, "name": "História" },
    { "id": 27, "name": "Terror" },
    { "id": 10402, "name": "Música" },
    { "id": 9648, "name": "Mistério" },
    { "id": 10749, "name": "Romance" },
    { "id": 878, "name": "Ficção científica" },
    { "id": 10770, "name": "Cinema TV" },
    { "id": 53, "name": "Thriller" },
    { "id": 10752, "name": "Guerra" },
    { "id": 37, "name": "Faroeste" }
  ],
  "results": [
    {
      "adult": false,
      "backdrop_path": "/czRXzKy5YcvoVhRUb8RQsFHUDi1.jpg",
      "genre_ids": [27],
      "id": 424139,
      "original_language": "en",
      "original_title": "Halloween",
      "overview": "Jamie Lee Curtis retorna à sua lendária personagem Laurie Strode, que chega a seu confronto final com Michael Myers, a criatura mascarada que a assombrou desde que ela escapou por um triz da matança na noite de Halloween, quatro décadas atrás.",
      "popularity": 61.867,
      "poster_path": "/bXs0zkv2iGVViZEy78teg2ycDBm.jpg",
      "release_date": "2018-10-18",
      "title": "Halloween",
      "video": false,
      "vote_average": 6.5,
      "vote_count": 3333
    },
    {
      "adult": false,
      "backdrop_path": "/uS9apevOgs2fuYghf9szOoK1u63.jpg",
      "genre_ids": [9648, 16, 28, 80],
      "id": 736073,
      "original_language": "en",
      "original_title": "Batman: The Long Halloween, Part One",
      "overview": "Um assassinato brutal no Halloween leva o jovem vigilante de Gotham, o Batman, a formar um pacto com o capitão da polícia James Gordan e o promotor Harvey Dent para derrubar The Roman, chefe da famigerada e poderosa Família Falcone do Crime. Depois que mais mortes ocorrem no Dia de Ação de Graças e no Natal, fica claro que eles estão lidando com um serial killer - a identidade de quem fica mais difícil de discernir a cada pista conflitante.",
      "popularity": 608.575,
      "poster_path": "/5QiyFLxCQNojxA6PUJwkgeE2HvD.jpg",
      "release_date": "2021-06-21",
      "title": "Batman:  O Longo Dia das Bruxas – Parte 1",
      "video": false,
      "vote_average": 7.8,
      "vote_count": 85
    },
    {
      "adult": false,
      "backdrop_path": "/5gTQmnGYKxDfmUWJ9GUWqrszRxN.jpg",
      "genre_ids": [10751, 16, 9648, 35],
      "id": 721656,
      "original_language": "en",
      "original_title": "Happy Halloween, Scooby-Doo!",
      "overview": "Scooby-Doo e a equipe se reúnem novamente para resolver o mistério de proporções gigantescas e salvar a Baía Cristal.",
      "popularity": 99.939,
      "poster_path": "/bs3p45IGZUZyqkHa4WLaiSk7xO9.jpg",
      "release_date": "2020-10-06",
      "title": "Scooby-Doo! Halloween",
      "video": false,
      "vote_average": 7.8,
      "vote_count": 136
    },
    {
      "adult": false,
      "backdrop_path": "/jj1jtNjYBx1CjVYtEylc9sWP0Jk.jpg",
      "genre_ids": [27, 53],
      "id": 610253,
      "original_language": "en",
      "original_title": "Halloween Kills",
      "overview": "Em Halloween Kills, depois de quatro décadas se preparando para enfrentar Michael Myers, Laurie Strode (Jamie Lee Curtis) acredita que enfim venceu. Porém, ela é surpreendida pelo retorno de seu grande inimigo em um novo desdobramento de mais um capítulo na saga Halloween.",
      "popularity": 69.504,
      "poster_path": "/5zPNs90yGHKdKadN2Bz32Pug8jY.jpg",
      "release_date": "2021-09-08",
      "title": "Halloween Kills: O Terror Continua",
      "video": false,
      "vote_average": 0,
      "vote_count": 0
    },
    {
      "adult": false,
      "backdrop_path": "/hDC6IpSg01T3QukfF9qkslQvWUF.jpg",
      "genre_ids": [27],
      "id": 2082,
      "original_language": "en",
      "original_title": "Halloween",
      "overview": "Aos 10 anos, Michael Myers é um garoto problemático, excluído por todos. Sua mãe é uma stripper no clube local e vive brigando com o namorado. Para descontar sua raiva do mundo, Michael tem o hábito de maltratar animais, até que um dia o diretor da escola descobre e informa à sua mãe que o garoto possui tendências psicopatas. Numa noite de Halloween, fantasiado com uma de suas máscaras preferidas, ele perde totalmente o controle, assassina todos na casa e vai parar num reformatório para crianças. Depois de ficar recluso por 17 anos, ele foge da instituição mental e retorna à cidade em busca de vingança. Qualquer um que atravessar seu caminho estará correndo um grave risco de morte.",
      "popularity": 32.102,
      "poster_path": "/aIoDPmYR9xSkQIUjqmjmu290lLW.jpg",
      "release_date": "2007-08-31",
      "title": "Halloween: O Início",
      "video": false,
      "vote_average": 6.2,
      "vote_count": 1550
    },
    {
      "adult": false,
      "backdrop_path": "/mNY25hRY6PzxjiRqpoqsWB6qHv9.jpg",
      "genre_ids": [27, 53],
      "original_language": "en",
      "original_title": "Halloween",
      "overview": "Na noite de Halloween de 1963, Michael Myers, de seis anos, assassina brutalmente sua irmã. Preso em uma instituição para doentes mentais sob os cuidados do dr. Sam Loomis, Michael cresce apenas para odiar. Em outubro de 1978, ele foge do hospital, seguido pelo dr. Loomis, que sabe que Michael vai matar novamente. O psicopata passa a perseguir a adolescente Laurie Strode e seus amigos, e prepara seu ataque mortal para a noite de Halloween.",
      "popularity": 27.621,
      "poster_path": "/xEYaxfz3g1CNyCugfj9NuontvVp.jpg",
      "release_date": "1978-10-24",
      "title": "Halloween - A Noite do Terror",
      "video": false,
      "vote_average": 7.6,
      "vote_count": 3587
    },
    {
      "adult": false,
      "backdrop_path": "/378twvs9moAbJ79uqZlNaZgxCwd.jpg",
      "genre_ids": [27],
      "original_language": "en",
      "original_title": "Halloween II",
      "overview": "O mal permanece vivo e toda a crueldade não é o bastante para Mike Myers. Ele continua com sua sede por sangue e não descansará enquanto sua irmã não o aceitar como membro da família. Ele torna-se ainda mais malvado, já que seu único laço com as emoções foi quebrado. Agora, há duas principais vítimas em seu caminho: sua irmã, a jovem Laurie e aquele que cuidou do rapaz durante sua temporada no manicômio, Dr. Samuel Loomis.",
      "popularity": 27.814,
      "poster_path": "/vSHPM4LQDpWdQrD5KZWK6wNqSOD.jpg",
      "release_date": "2009-08-28",
      "title": "Halloween II",
      "video": false,
      "vote_average": 5.4,
      "vote_count": 907
    },
    {
      "adult": false,
      "backdrop_path": "/9QLbm8pncT3jHjVjyYfHrbqrht.jpg",
      "genre_ids": [27, 53],
      "original_language": "en",
      "original_title": "Halloween: Resurrection",
      "overview": "Um grupo de adolescentes ganha um concurso para passar uma noite na casa de Michael Myers para uma exibição ao vivo pela TV. A intenção é se divertir e se promover. Mas, as coisas ficam assustadoras e o jogo se transforma numa luta onde nem todos saem vivos",
      "popularity": 26.204,
      "poster_path": "/z2yPytnzLZQtQONX9DLH4FR3Iet.jpg",
      "release_date": "2002-07-01",
      "title": "Halloween: Ressurreição",
      "video": false,
      "vote_average": 4.6,
      "vote_count": 802
    },
    {
      "adult": false,
      "backdrop_path": "/rRUZMxzNqVem03J9266sx1lnCQ0.jpg",
      "genre_ids": [27],
      "original_language": "en",
      "original_title": "Halloween II",
      "overview": "Em \"Halloween II: O Pesadelo Continua\", os mesmos personagens amaldiçoados reencontram o maníaco da faca, que todos acreditavam estar morto. Mas... o desumano Michael Myers está vivo e ainda mais sedento de vingança. Depois de passar quinze anos em um hospício, o aparentemente indestrutível Myers está a procura de sua irmã. À medida que chega perto de seu alvo, o Dr. Loomis descobre os mistérios horripilantes que há por trás dos atos selvagens do psicopata enfurecido e tenta detê-lo. Myers não poupará ninguém que cruzar seu caminho.",
      "popularity": 22.348,
      "poster_path": "/3wCCqM7JSSt6PJFNMEC2fxflDjP.jpg",
      "release_date": "1981-10-30",
      "title": "Halloween II: O Pesadelo Continua",
      "video": false,
      "vote_average": 6.5,
      "vote_count": 1243
    },
    {
      "adult": false,
      "backdrop_path": "/aOeshAxAhiDVIiHsXVFmF6bgclh.jpg",
      "genre_ids": [35, 14, 9648, 27],
      "id": 617505,
      "original_language": "en",
      "original_title": "Hubie Halloween",
      "overview": "Hubie não é muito popular em Salém, mas quando o Halloween começa a ficar assustador de verdade, esse cara bonzinho e medroso faz de tudo para salvar a cidade.",
      "popularity": 18.787,
      "poster_path": "/AhWYlsPynRZtyJH6MTsiuLGOCNu.jpg",
      "release_date": "2020-10-07",
      "title": "O Halloween do Hubie",
      "video": false,
      "vote_average": 6.1,
      "vote_count": 1017
    },
    {
      "adult": false,
      "backdrop_path": "/h5BvesqaxL7V3vl1CmaR8waGyiM.jpg",
      "genre_ids": [12, 35, 14, 10751, 27],
      "id": 442062,
      "original_language": "en",
      "original_title": "Goosebumps 2: Haunted Halloween",
      "overview": "Wardenclyffe, Estados Unidos, às vésperas do Halloween. Sonny (Jeremy Ray Taylor) e Sam (Caleel Harris) são grandes amigos, que encontram um livro incompleto guardado dentro de um baú, em uma casa abandonada. Ao abri-lo, eles despertam o boneco Slappy (Avery Lee Jones), que surge inesperadamente. Criação do autor R.L. Stine (Jack Black), ele usa os jovens e ainda a irmã de Sonny, Sarah (Madison Iseman), para criar sua própria família de monstros.",
      "popularity": 32.092,
      "poster_path": "/bRLs9vwtcTUMSoMepqnHT6u7GTN.jpg",
      "release_date": "2018-10-11",
      "title": "Goosebumps 2: Halloween Assombrado",
      "video": false,
      "vote_average": 6.1,
      "vote_count": 1025
    },
    {
      "adult": false,
      "backdrop_path": null,
      "genre_ids": [27, 53],
      "original_language": "en",
      "original_title": "Halloween Ends",
      "overview": "",
      "popularity": 14.716,
      "poster_path": "/tfnVnSV9Y24VWBoglBptMb1F7vy.jpg",
      "release_date": "2022-10-13",
      "title": "Halloween Ends",
      "video": false,
      "vote_average": 0,
      "vote_count": 0
    },
    {
      "adult": false,
      "backdrop_path": "/j0g1176cyn4IrjPNvuEzwZraZf8.jpg",
      "genre_ids": [27, 53],
      "original_language": "en",
      "original_title": "Halloween 4: The Return of Michael Myers",
      "overview": "Dez anos depois de seu massacre, o doentio Michael Myers está sendo transferido do sanatório de doentes mentais de Richmond, quando foge exatamente no dia de Halloween e vai atrás da sua sobrinha de sete anos, para matá-la. Conseguirá o Dr. Loomis impedir a investida de terror criada por Myers?",
      "popularity": 40.488,
      "poster_path": "/myrvDo899AFkxtSl7ELxprly0mz.jpg",
      "release_date": "1988-10-21",
      "title": "Halloween 4: O Retorno de Michael Myers",
      "video": false,
      "vote_average": 6,
      "vote_count": 853
    },
    {
      "adult": false,
      "backdrop_path": "/ihQyd9K5ca5sF3w1HwE8IgwMXl7.jpg",
      "genre_ids": [27, 53],
      "id": 610359,
      "original_language": "en",
      "original_title": "On Halloween",
      "overview": "Um jornalista vai em busca da verdade depois de uma série de mortes brutais e desaparecimentos. Isso traz de volta uma lenda urbana sobre um palhaço assassino em série que persegue a floresta de Century Park por mais de cem anos.",
      "popularity": 10.272,
      "poster_path": "/5rsEhgcNRUthjo6fqRDqZy5plx.jpg",
      "release_date": "2020-10-09",
      "title": "On Halloween",
      "video": false,
      "vote_average": 6.7,
      "vote_count": 43
    },
    {
      "adult": false,
      "backdrop_path": "/jCgPIpNbJF7lm0YIo3xY10A3R74.jpg",
      "genre_ids": [27, 53],
      "id": 11361,
      "original_language": "en",
      "original_title": "Halloween 5: The Revenge of Michael Myers",
      "overview": "Um ano após os eventos do Dia das Bruxas, Michael sobrevive aos tiroteio e em 31 de outubro retorna sedento de vingança. Espreita e persegue, Jamie, Rachel, e amigos de Rachel, Michael faz um plano para seduzir Jamie fora do hospital infantil, onde aconteceram os eventos que levam até o confronto na casa de Myers.",
      "popularity": 30.081,
      "poster_path": "/d4wUOBFhyzmUnsbJgL8wMt9CJfU.jpg",
      "release_date": "1989-10-12",
      "title": "Halloween 5: A Vingança de Michael Myers",
      "video": false,
      "vote_average": 5.4,
      "vote_count": 706
    },
    {
      "adult": false,
      "backdrop_path": "/o1Rn4j1PPcJUXsRL02mWXUw3BrF.jpg",
      "genre_ids": [27, 53],
      "id": 11675,
      "original_language": "en",
      "original_title": "Halloween H20: 20 Years Later",
      "overview": "Depois de escapar do assassino mascarado, Laurie Strode forjou sua morte e reconstruiu sua vida mudando de nome e cidade. Agora, vinte anos mais tarde, Laurie e Michael Myers estão prestes a se encontrarem novamente. Ele volta em busca de vingança, mas não é somente atrás dela que ele está. O terror começa para toda a nova geração...",
      "popularity": 17.213,
      "poster_path": "/ar9FNoPuelrp3tJRWu6vgjC7bjF.jpg",
      "release_date": "1998-08-05",
      "title": "Halloween H20: 20 Anos Depois",
      "video": false,
      "vote_average": 6,
      "vote_count": 1065
    },
    {
      "adult": false,
      "backdrop_path": "/kqpVQfGQyADVGX0ZhAO2KvvYOZR.jpg",
      "genre_ids": [10770, 27, 878],
      "id": 229839,
      "original_language": "en",
      "original_title": "Grave Halloween",
      "overview": "A Floresta do Suicídio, localizada no Japão, é apenas um nome, não é? Miko pretende descobrir, mesmo que isso signifique revelar a triste verdade sobre sua mãe morta.",
      "popularity": 9.272,
      "poster_path": "/oQdlK4U4VecCvVwaGi1nEtsD5my.jpg",
      "release_date": "2013-10-19",
      "title": "Floresta dos Suicidas",
      "video": false,
      "vote_average": 4.6,
      "vote_count": 48
    },
    {
      "adult": false,
      "backdrop_path": "/eyOKqtgNeEEIp7zYMHnpISpsaS3.jpg",
      "genre_ids": [27],
      "id": 10676,
      "original_language": "en",
      "original_title": "Halloween III: Season of the Witch",
      "overview": "Todos os pesadelos de qualquer pai estão retratados neste filme sobre possessão de milhões de crianças na noite de Halloween. \"Halloween III: A Noite das Bruxas\" é uma história que tem a sua origem no culto através de mascaras mágicas que uma vez usadas pelas crianças ficam possuídas pelas forças do mal que se apoderam dos seus corpos e mentes. É pois esta luta do Bem contra o Mal que vamos reviver neste espectacular filme.",
      "popularity": 20.896,
      "poster_path": "/pzM1bZ7kzi3bgix13PLuXIJuJqt.jpg",
      "release_date": "1982-10-22",
      "title": "Halloween III: A Noite das Bruxas",
      "video": false,
      "vote_average": 5.1,
      "vote_count": 811
    },
    {
      "adult": false,
      "backdrop_path": "/c0XKcEX1IvqDUkOlt8XrmKh1AtI.jpg",
      "genre_ids": [27, 53],
      "id": 10987,
      "original_language": "en",
      "original_title": "Halloween: The Curse of Michael Myers",
      "overview": "Seis anos depois que Michael Myers aterrorizou Haddonfield, Illinois, pela última vez, ele volta para lá em busca de sua sobrinha, Jamie Lloyd, que escapou com seu filho recém-nascido, para o qual Michael e um culto misterioso têm planos sinistros.",
      "popularity": 20.711,
      "poster_path": "/6y6ldKKz8x6h5r0l9WpLXeiA5IS.jpg",
      "release_date": "1995-09-29",
      "title": "Halloween 6: A Última Vingança",
      "video": false,
      "vote_average": 5.2,
      "vote_count": 653
    },
    {
      "adult": false,
      "backdrop_path": "/7WuVUAsWWHt4g11R1HalX0RX2bh.jpg",
      "genre_ids": [16, 28, 80, 9648],
      "id": 736074,
      "original_language": "en",
      "original_title": "Batman: The Long Halloween, Part Two",
      "overview": "",
      "popularity": 22.326,
      "poster_path": "/5X1n5q08mZ7NpNpxehMFODxfNYq.jpg",
      "release_date": "2021-07-26",
      "title": "Batman:  O Longo Dia das Bruxas – Parte 2",
      "video": false,
      "vote_average": 0,
      "vote_count": 0
    }
  ]
}
